{
  "area": [
    {
      "id": 1,
      "name": "finances",
      "userInCharge": "Jose",
      "amountOfEmployees": 4,
      "active": true
    },
    {
      "id": 11,
      "name": "finances",
      "userInCharge": "Jose",
      "amountOfEmployees": 4,
      "active": false
    },
    {
      "name": "ventas",
      "active": false,
      "id": 12,
      "userInCharge": "test user",
      "amountOfEmployees": 0
    }
  ],
  "asset": [
    {
      "id": 1,
      "type": "computer",
      "model": "macbook",
      "condition": "usado",
      "areaId": 1,
      "active": true
    },
    {
      "type": "perifericos",
      "model": "2023",
      "condition": "nuevo",
      "areaId": 1,
      "id": 2,
      "active": true
    },
    {
      "type": "asdfasdfadsf",
      "model": "asdf",
      "condition": "nuevo",
      "areaId": null,
      "active": true,
      "id": 3
    },
    {
      "type": "ewewe",
      "model": "wewww",
      "condition": "desuso",
      "areaId": null,
      "active": true,
      "id": 4
    }
  ],
  "categories": [
    {
      "name": "Gaseosas",
      "active": true,
      "id": 1
    },
    {
      "name": "Jueguetes",
      "active": true,
      "id": 2
    }
  ],
  "products": [
    {
      "id": 1,
      "name": "Pepsi",
      "price": 11,
      "categoryId": 1
    },
    {
      "name": "Fanta",
      "price": "14",
      "categoryId": 1,
      "id": 3
    },
    {
      "name": "Pelota",
      "price": "50",
      "categoryId": 2,
      "id": 4
    }
  ]
}